MANIFEST.in
README.rst
setup.py
/Users/barbuza/Sites/raygun4py/python2/raygun4py/__init__.py
/Users/barbuza/Sites/raygun4py/python2/raygun4py/cli.py
/Users/barbuza/Sites/raygun4py/python2/raygun4py/raygunmsgs.py
/Users/barbuza/Sites/raygun4py/python2/raygun4py/raygunprovider.py
/Users/barbuza/Sites/raygun4py/python2/raygun4py/utilities.py
/Users/barbuza/Sites/raygun4py/python2/raygun4py/middleware/__init__.py
/Users/barbuza/Sites/raygun4py/python2/raygun4py/middleware/django.py
/Users/barbuza/Sites/raygun4py/python2/raygun4py/middleware/flask.py
/Users/barbuza/Sites/raygun4py/python2/raygun4py/middleware/wsgi.py
/Users/barbuza/Sites/raygun4py/python3/raygun4py/__init__.py
/Users/barbuza/Sites/raygun4py/python3/raygun4py/cli.py
/Users/barbuza/Sites/raygun4py/python3/raygun4py/raygunmsgs.py
/Users/barbuza/Sites/raygun4py/python3/raygun4py/raygunprovider.py
/Users/barbuza/Sites/raygun4py/python3/raygun4py/utilities.py
/Users/barbuza/Sites/raygun4py/python3/raygun4py/middleware/__init__.py
/Users/barbuza/Sites/raygun4py/python3/raygun4py/middleware/django.py
/Users/barbuza/Sites/raygun4py/python3/raygun4py/middleware/flask.py
/Users/barbuza/Sites/raygun4py/python3/raygun4py/middleware/wsgi.py
python2/raygun4py/__init__.py
python2/raygun4py/cli.py
python2/raygun4py/raygunmsgs.py
python2/raygun4py/raygunprovider.py
python2/raygun4py/utilities.py
python2/raygun4py/middleware/__init__.py
python2/raygun4py/middleware/django.py
python2/raygun4py/middleware/flask.py
python2/raygun4py/middleware/wsgi.py
python2/samples/sample.py
python2/samples/sampleWithLogging.py
python2/tests/__init__.py
python2/tests/test_functional.py
python2/tests/test_raygunmsgs.py
python2/tests/test_raygunprovider.py
python2/tests/middleware/__init__.py
python2/tests/middleware/test_django.py
python3/raygun4py/__init__.py
python3/raygun4py/cli.py
python3/raygun4py/raygunmsgs.py
python3/raygun4py/raygunprovider.py
python3/raygun4py/utilities.py
python3/raygun4py/middleware/__init__.py
raygun4py_alt.egg-info/PKG-INFO
raygun4py_alt.egg-info/SOURCES.txt
raygun4py_alt.egg-info/dependency_links.txt
raygun4py_alt.egg-info/entry_points.txt
raygun4py_alt.egg-info/requires.txt
raygun4py_alt.egg-info/top_level.txt